llm_labeling_ui/__init__.py
llm_labeling_ui/api.py
llm_labeling_ui/cluster.py
llm_labeling_ui/cluster_cmd.py
llm_labeling_ui/const.py
llm_labeling_ui/conversation_cmd.py
llm_labeling_ui/db_schema.py
llm_labeling_ui/main.py
llm_labeling_ui/schema.py
llm_labeling_ui/server_cmd.py
llm_labeling_ui/tag_cmd.py
llm_labeling_ui/utils.py
llm_labeling_ui/lang_classification/__init__.py
llm_labeling_ui/out/404.html
llm_labeling_ui/out/favicon.ico
llm_labeling_ui/out/index.html
llm_labeling_ui/out/screenshot.png
llm_labeling_ui/out/_next/static/2kpme7mOzk38i-LPIoNZ4/_buildManifest.js
llm_labeling_ui/out/_next/static/2kpme7mOzk38i-LPIoNZ4/_ssgManifest.js
llm_labeling_ui/out/_next/static/44BvdhJbyjOF8FefRiR1H/_buildManifest.js
llm_labeling_ui/out/_next/static/44BvdhJbyjOF8FefRiR1H/_ssgManifest.js
llm_labeling_ui/out/_next/static/5_lm8fq70dCfCr1JHj5z0/_buildManifest.js
llm_labeling_ui/out/_next/static/5_lm8fq70dCfCr1JHj5z0/_ssgManifest.js
llm_labeling_ui/out/_next/static/Ap9WSD2qImLholrpgeFhC/_buildManifest.js
llm_labeling_ui/out/_next/static/Ap9WSD2qImLholrpgeFhC/_ssgManifest.js
llm_labeling_ui/out/_next/static/FYCrwyLUNzQI8UTahYrwi/_buildManifest.js
llm_labeling_ui/out/_next/static/FYCrwyLUNzQI8UTahYrwi/_ssgManifest.js
llm_labeling_ui/out/_next/static/HPIT1gE90PtEI8Mrmfz8p/_buildManifest.js
llm_labeling_ui/out/_next/static/HPIT1gE90PtEI8Mrmfz8p/_ssgManifest.js
llm_labeling_ui/out/_next/static/I9aLZejVfhBcpFAzXvCKc/_buildManifest.js
llm_labeling_ui/out/_next/static/I9aLZejVfhBcpFAzXvCKc/_ssgManifest.js
llm_labeling_ui/out/_next/static/L9O6kF5OZ-Mo07zTmAV5b/_buildManifest.js
llm_labeling_ui/out/_next/static/L9O6kF5OZ-Mo07zTmAV5b/_ssgManifest.js
llm_labeling_ui/out/_next/static/P4-yGsJ8vuu3J0exIkLfC/_buildManifest.js
llm_labeling_ui/out/_next/static/P4-yGsJ8vuu3J0exIkLfC/_ssgManifest.js
llm_labeling_ui/out/_next/static/UOoaaNIeixhSiDb-quUt6/_buildManifest.js
llm_labeling_ui/out/_next/static/UOoaaNIeixhSiDb-quUt6/_ssgManifest.js
llm_labeling_ui-0.10.2.dist-info/METADATA
llm_labeling_ui-0.10.2.dist-info/WHEEL
llm_labeling_ui-0.10.2.dist-info/entry_points.txt
llm_labeling_ui-0.10.2.dist-info/top_level.txt
llm_labeling_ui-0.10.2.dist-info/RECORD
