Metadata-Version: 2.1
Name: llm-labeling-ui
Version: 0.10.2
Summary: LLM Labeling UI is an open source project for large language model data labeling
Home-page: https://github.com/Sanster/llm-labeling-ui
Author: PanicByte
Author-email: cwq1913@gmail.com
Classifier: License :: OSI Approved :: Apache Software License
Classifier: Operating System :: OS Independent
Classifier: Programming Language :: Python :: 3
Classifier: Programming Language :: Python :: 3.7
Classifier: Programming Language :: Python :: 3.8
Classifier: Programming Language :: Python :: 3.9
Classifier: Programming Language :: Python :: 3.10
Classifier: Topic :: Scientific/Engineering :: Artificial Intelligence
Requires-Python: >=3.7
Requires-Dist: openai
Requires-Dist: fastapi
Requires-Dist: loguru
Requires-Dist: typer
Requires-Dist: pydantic
Requires-Dist: rich
Requires-Dist: sqlmodel
Requires-Dist: transformers
Requires-Dist: gunicorn
Requires-Dist: uvicorn
Requires-Dist: pygtrie
Requires-Dist: fasttext
Requires-Dist: pandas
Requires-Dist: tqdm
Requires-Dist: more-itertools
